thunderseg/__init__.py
thunderseg/_version.py
thunderseg/main.py
thunderseg/core/__init__.py
thunderseg/core/postprocess.py
thunderseg/core/preprocess.py
thunderseg/core/train.py
thunderseg/model/__init__.py
thunderseg/model/maskrcnn_ms.py
thunderseg/model/maskrcnn_rgb.py
thunderseg/utils/__init__.py
thunderseg/utils/config.toml
thunderseg/utils/debug.py
thunderseg/utils/error_handle.py
thunderseg/utils/tool.py
thunderseg-1.0.0.dist-info/METADATA
thunderseg-1.0.0.dist-info/WHEEL
thunderseg-1.0.0.dist-info/entry_points.txt
thunderseg-1.0.0.dist-info/top_level.txt
thunderseg-1.0.0.dist-info/RECORD
