Metadata-Version: 2.2
Name: thunderseg
Version: 1.0.0
Summary: A deep learning framwork focus on image segmentation
Author-email: Jiawei Li <Jiaweiliwork@outlook.com>
Classifier: Programming Language :: Python :: 3
Classifier: License :: OSI Approved :: MIT License
Classifier: Operating System :: OS Independent
